{
  "": "",
  " ARTICLES PAGE": "",
  "ARTICLE": "",
  "ARTICLE DETAILS PAGE": "",
  "C аватар": "",
  "Comments": "",
  "Loading": {
    "": {
      "": {
        "": ""
      }
    }
  },
  "MainPage": "",
  "Page not found": "",
  "Profile Page": "",
  "throw error": "",
  "toggle": "",
  "Айти": "",
  "Ваш": "",
  "Ваш аватар": "",
  "Ваш возраст": "",
  "Ваш город": "",
  "Ваш город ": "",
  "Ваш ник": "",
  "Ваша фамилия": "",
  "Ваше": "",
  "Ваше имя": "",
  "Введите имя пользователя": "",
  "Введите пароль": "",
  "Введите текст комментария": "",
  "Войти": "",
  "Все": "",
  "Вы ввели неправильный логин или пароль": "",
  "Выйти": "",
  "Главная": "",
  "Комментарии": "",
  "Комментарии отсутствуют": "",
  "Наука": "",
  "Неверные данные пользователя": "",
  "Неправильная страна": "",
  "Неправильно указана страна": "",
  "Неправильный возраст": "",
  "Нет данных": "",
  "О": "",
  "О сайте": "",
  "Обновите страницу": "",
  "Отмена": "",
  "Отправить": "",
  "Ошибка сервера": "",
  "Перезагрузить страницу": "",
  "Плитка": "",
  "По возрастанию": "",
  "По убыванию": "",
  "Поиск": "",
  "Прои": "",
  "Произошла какая-то ошибка": "",
  "Произошла ошибка": "",
  "Профиль": "",
  "Профиль пользователя": "",
  "Редактировать": "",
  "Сортировать": "",
  "Сортировать ПО": "",
  "Сох": "",
  "Сохранить": "",
  "Список": "",
  "Ссылка на аватар": "",
  "Статьи не найдены": "",
  "Статья не найдена": "",
  "Страница не найдена": "",
  "Укажите валюту": "",
  "Укажите страну": "",
  "Форма авторизации": "",
  "Читать далее": "",
  "Экономика": "",
  "Язык": "",
  "возрастанию": "",
  "дате созданию": "",
  "дате создания": "",
  "количеству просмотров": "",
  "названию": "",
  "по": "",
  "созданию": "",
  "убыванию": ""
}
